README.rst
setup.py
es/__init__.py
es/fields.py
es/publisher.py
es.egg-info/PKG-INFO
es.egg-info/SOURCES.txt
es.egg-info/dependency_links.txt
es.egg-info/not-zip-safe
es.egg-info/top_level.txt
es/aggregate/__init__.py
es/aggregate/base.py
es/aggregate/meta.py
es/aggregate/options.py
es/aggregate/state.py
es/event/__init__.py
es/event/base.py
es/event/meta.py
es/persistence/__init__.py
es/persistence/ieventstore.py
es/persistence/memory/__init__.py
es/persistence/sql/__init__.py
es/persistence/sql/eventstore.py
es/persistence/sql/orm.py
es/test/__init__.py
tests/__init__.py
tests/integration/__init__.py
tests/integration/test_event_handling.py
tests/integration/test_persistence.py